LICENSE.txt
README.md
setup.py
ouddane_rocket/__init__.py
ouddane_rocket/ouddane_rocket.py
ouddane_rocket.egg-info/PKG-INFO
ouddane_rocket.egg-info/SOURCES.txt
ouddane_rocket.egg-info/dependency_links.txt
ouddane_rocket.egg-info/requires.txt
ouddane_rocket.egg-info/top_level.txt