Metadata-Version: 2.1
Name: ouddane_rocket
Version: 1.0.0
Summary: An awesome package that does something
Home-page: http://pypi.python.org/pypi/ouddane_rocket/
Author: ouddane youcef
Author-email: yousefouddane3@gmail.com
License: LICENSE.txt
License-File: LICENSE.txt
Requires-Dist: ouddane_rocket
